{
	"name": "Enemy",
	"plugin-id": "Sprite",
	"sid": 400496834358730,
	"isGlobal": false,
	"instanceVariables": [
		{
			"name": "EnemyName",
			"type": "string",
			"desc": "",
			"sid": 504049916290819
		},
		{
			"name": "EnemyType",
			"type": "string",
			"desc": "",
			"sid": 327584574093164
		}
	],
	"behaviorTypes": [
		{
			"behaviorId": "MoveTo",
			"name": "MoveTo",
			"sid": 583860230820250
		}
	],
	"effectTypes": [],
	"animations": {
		"items": [
			{
				"frames": [
					{
						"width": 250,
						"height": 250,
						"originX": 0.5,
						"originY": 0.5,
						"originalSource": "",
						"exportFormat": "png",
						"exportQuality": 0.8,
						"imageSpriteId": 4405852,
						"useCollisionPoly": true,
						"duration": 1
					}
				],
				"sid": 906184904694163,
				"name": "Animation 1",
				"isLooping": false,
				"isPingPong": false,
				"repeatCount": 1,
				"repeatTo": 0,
				"speed": 5
			}
		],
		"subfolders": []
	}
}